surf_scrap/__init__.py
surf_scrap/scraper.py
surf_scrap_cli-1.0.1.dist-info/METADATA
surf_scrap_cli-1.0.1.dist-info/WHEEL
surf_scrap_cli-1.0.1.dist-info/entry_points.txt
surf_scrap_cli-1.0.1.dist-info/top_level.txt
surf_scrap_cli-1.0.1.dist-info/RECORD
