Metadata-Version: 2.4
Name: surf_scrap_cli
Version: 1.0.1
Summary: Extraction des données météo surf depuis surf-report.com
Home-page: https://github.com/votre-username/surf_scrap
Author: Céline ADOUSSINGANDE, Loukmane BOULANKI, Isaac BESSANH
Author-email: mauriceteadoussinande@yahoo.com
Classifier: Programming Language :: Python :: 3
Classifier: License :: OSI Approved :: MIT License
Classifier: Operating System :: OS Independent
Requires-Python: >=3.7
Requires-Dist: requests>=2.25.0
Requires-Dist: beautifulsoup4>=4.9.0
Requires-Dist: pandas>=1.2.0
Requires-Dist: lxml>=4.6.0
Dynamic: author
Dynamic: author-email
Dynamic: classifier
Dynamic: description
Dynamic: description-content-type
Dynamic: home-page
Dynamic: requires-dist
Dynamic: requires-python
Dynamic: summary
